odoo/addons/epi/__init__.py
odoo/addons/epi/__manifest__.py
odoo/addons/epi/i18n/ca_ES.po
odoo/addons/epi/i18n/es.po
odoo/addons/epi/models/__init__.py
odoo/addons/epi/models/res_company.py
odoo/addons/epi/views/report_invoice.xml
odoo/addons/epi/views/report_templates.xml
odoo/addons/epi/views/res_company_views.xml
odoo/addons/epi/views/sale_report_templates.xml
odoo12_addon_epi-12.0.0.1.0.dist-info/METADATA
odoo12_addon_epi-12.0.0.1.0.dist-info/WHEEL
odoo12_addon_epi-12.0.0.1.0.dist-info/top_level.txt
odoo12_addon_epi-12.0.0.1.0.dist-info/RECORD
